LICENSE.md
MANIFEST.in
README.md
requirements.txt
setup.cfg
setup.py
repofinder/__init__.py
repofinder/app.py
repofinder/config.py
repofinder/query.py
repofinder/repository.py
repofinder.egg-info/PKG-INFO
repofinder.egg-info/SOURCES.txt
repofinder.egg-info/dependency_links.txt
repofinder.egg-info/requires.txt
repofinder.egg-info/top_level.txt
tests/__init__.py
tests/test_config.py
tests/test_query.py