Metadata-Version: 2.1
Name: repofinder
Version: 0.1.1
Summary: Find repo for your first contribution!.
Home-page: https://github.com/mateuszz0000/repofinder
Author: mateuszz0000
Author-email: mtszzwdzk@gmail.com
License: UNKNOWN
Download-URL: https://github.com/mateuszz0000/repofinder/archive/v_0.1.tar.gz
Platform: UNKNOWN
Classifier: Programming Language :: Python :: 3
Classifier: License :: OSI Approved :: MIT License
Classifier: Operating System :: OS Independent
Requires-Python: >=3.6
